{
  "project_info": {
    "project_number": "426288381609",
    "project_id": "nukogram",
    "storage_bucket": "nukogram.appspot.com"
  },
  "client": [
    {
      "client_info": {
        "mobilesdk_app_id": "1:426288381609:android:be8b286e658027c238f3b8",
        "android_client_info": {
          "package_name": "cc.sukazyo.nukogram"
        }
      },
      "oauth_client": [
        {
          "client_id": "426288381609-u3fppdp7ej2k40tm5edai86g4mh8ht7v.apps.googleusercontent.com",
          "client_type": 3
        }
      ],
      "api_key": [
        {
          "current_key": "AIzaSyCg7mGYE4vBvFYuYQ14Wg77Pk4wb_G84-s"
        }
      ],
      "services": {
        "appinvite_service": {
          "other_platform_oauth_client": [
            {
              "client_id": "426288381609-u3fppdp7ej2k40tm5edai86g4mh8ht7v.apps.googleusercontent.com",
              "client_type": 3
            }
          ]
        }
      }
    },
    {
      "client_info": {
        "mobilesdk_app_id": "1:426288381609:android:925f3f99c00cbbc438f3b8",
        "android_client_info": {
          "package_name": "cc.sukazyo.nukogram.beta"
        }
      },
      "oauth_client": [
        {
          "client_id": "426288381609-u3fppdp7ej2k40tm5edai86g4mh8ht7v.apps.googleusercontent.com",
          "client_type": 3
        }
      ],
      "api_key": [
        {
          "current_key": "AIzaSyCg7mGYE4vBvFYuYQ14Wg77Pk4wb_G84-s"
        }
      ],
      "services": {
        "appinvite_service": {
          "other_platform_oauth_client": [
            {
              "client_id": "426288381609-u3fppdp7ej2k40tm5edai86g4mh8ht7v.apps.googleusercontent.com",
              "client_type": 3
            }
          ]
        }
      }
    }
  ],
  "configuration_version": "1"
}